{"@t":"2020-07-03T08:12:58.4830994Z","@mt":"{StartMessage} [Timing {TimingId}]","StartMessage":"Booting Umbraco 8.6.3.","TimingId":"193fc46","SourceContext":"Umbraco.Core.Runtime.CoreRuntime","ProcessId":19484,"ProcessName":"iisexpress","ThreadId":1,"AppDomainId":2,"AppDomainAppId":"LMW3SVC2ROOT","MachineName":"MSI","Log4NetLevel":"INFO ","HttpRequestNumber":1,"HttpRequestId":"f4148f5d-2b9c-4a72-a666-bf1a33720670"}
{"@t":"2020-07-03T08:12:58.5090993Z","@mt":"Booting site '{HostingSiteName}', app '{HostingApplicationID}', path '{HostingPhysicalPath}', server '{MachineName}'.","HostingSiteName":"Emi-Center","HostingApplicationID":"/LM/W3SVC/2/ROOT","HostingPhysicalPath":"C:\\Users\\pisaq\\source\\repos\\Emi-Center\\","MachineName":"MSI","SourceContext":"Umbraco.Core.Runtime.CoreRuntime","ProcessId":19484,"ProcessName":"iisexpress","ThreadId":1,"AppDomainId":2,"AppDomainAppId":"LMW3SVC2ROOT","Log4NetLevel":"INFO ","HttpRequestNumber":1,"HttpRequestId":"f4148f5d-2b9c-4a72-a666-bf1a33720670"}
{"@t":"2020-07-03T08:12:58.7181002Z","@mt":"Acquiring.","SourceContext":"Umbraco.Core.Runtime.MainDom","ProcessId":19484,"ProcessName":"iisexpress","ThreadId":1,"AppDomainId":2,"AppDomainAppId":"LMW3SVC2ROOT","MachineName":"MSI","Log4NetLevel":"INFO ","HttpRequestNumber":1,"HttpRequestId":"f4148f5d-2b9c-4a72-a666-bf1a33720670"}
{"@t":"2020-07-03T08:12:58.7201021Z","@mt":"Acquired.","SourceContext":"Umbraco.Core.Runtime.MainDom","ProcessId":19484,"ProcessName":"iisexpress","ThreadId":1,"AppDomainId":2,"AppDomainAppId":"LMW3SVC2ROOT","MachineName":"MSI","Log4NetLevel":"INFO ","HttpRequestNumber":1,"HttpRequestId":"f4148f5d-2b9c-4a72-a666-bf1a33720670"}
{"@t":"2020-07-03T08:12:59.8341053Z","@mt":"{StartMessage} [Timing {TimingId}]","StartMessage":"Resolving composer types.","TimingId":"7e89351","SourceContext":"Umbraco.Core.Runtime.CoreRuntime","ProcessId":19484,"ProcessName":"iisexpress","ThreadId":1,"AppDomainId":2,"AppDomainAppId":"LMW3SVC2ROOT","MachineName":"MSI","Log4NetLevel":"INFO ","HttpRequestNumber":1,"HttpRequestId":"f4148f5d-2b9c-4a72-a666-bf1a33720670"}
{"@t":"2020-07-03T08:12:59.9950992Z","@mt":"{EndMessage} ({Duration}ms) [Timing {TimingId}]","EndMessage":"Resolved.","Duration":159,"TimingId":"7e89351","SourceContext":"Umbraco.Core.Runtime.CoreRuntime","ProcessId":19484,"ProcessName":"iisexpress","ThreadId":1,"AppDomainId":2,"AppDomainAppId":"LMW3SVC2ROOT","MachineName":"MSI","Log4NetLevel":"INFO ","HttpRequestNumber":1,"HttpRequestId":"f4148f5d-2b9c-4a72-a666-bf1a33720670"}
{"@t":"2020-07-03T08:13:04.6571013Z","@mt":"Registered with MainDom, localContentDbExists? {LocalContentDbExists}, localMediaDbExists? {LocalMediaDbExists}","LocalContentDbExists":true,"LocalMediaDbExists":true,"SourceContext":"Umbraco.Web.PublishedCache.NuCache.PublishedSnapshotService","ProcessId":19484,"ProcessName":"iisexpress","ThreadId":1,"AppDomainId":2,"AppDomainAppId":"LMW3SVC2ROOT","MachineName":"MSI","Log4NetLevel":"INFO ","HttpRequestNumber":1,"HttpRequestId":"f4148f5d-2b9c-4a72-a666-bf1a33720670"}
{"@t":"2020-07-03T08:13:04.6571013Z","@mt":"Creating the content store, localContentDbExists? {LocalContentDbExists}","LocalContentDbExists":true,"SourceContext":"Umbraco.Web.PublishedCache.NuCache.PublishedSnapshotService","ProcessId":19484,"ProcessName":"iisexpress","ThreadId":1,"AppDomainId":2,"AppDomainAppId":"LMW3SVC2ROOT","MachineName":"MSI","Log4NetLevel":"INFO ","HttpRequestNumber":1,"HttpRequestId":"f4148f5d-2b9c-4a72-a666-bf1a33720670"}
{"@t":"2020-07-03T08:13:04.6591020Z","@mt":"Creating the media store, localMediaDbExists? {LocalMediaDbExists}","LocalMediaDbExists":true,"SourceContext":"Umbraco.Web.PublishedCache.NuCache.PublishedSnapshotService","ProcessId":19484,"ProcessName":"iisexpress","ThreadId":1,"AppDomainId":2,"AppDomainAppId":"LMW3SVC2ROOT","MachineName":"MSI","Log4NetLevel":"INFO ","HttpRequestNumber":1,"HttpRequestId":"f4148f5d-2b9c-4a72-a666-bf1a33720670"}
{"@t":"2020-07-03T08:13:05.4040989Z","@mt":"{StartMessage} [Timing {TimingId}]","StartMessage":"Loading content from local cache file","TimingId":"8b7a4c8","SourceContext":"Umbraco.Web.PublishedCache.NuCache.PublishedSnapshotService","ProcessId":19484,"ProcessName":"iisexpress","ThreadId":1,"AppDomainId":2,"AppDomainAppId":"LMW3SVC2ROOT","MachineName":"MSI","Log4NetLevel":"INFO ","HttpRequestNumber":1,"HttpRequestId":"f4148f5d-2b9c-4a72-a666-bf1a33720670"}
{"@t":"2020-07-03T08:13:05.4370993Z","@mt":"{EndMessage} ({Duration}ms) [Timing {TimingId}]","EndMessage":"Completed.","Duration":32,"TimingId":"8b7a4c8","SourceContext":"Umbraco.Web.PublishedCache.NuCache.PublishedSnapshotService","ProcessId":19484,"ProcessName":"iisexpress","ThreadId":1,"AppDomainId":2,"AppDomainAppId":"LMW3SVC2ROOT","MachineName":"MSI","Log4NetLevel":"INFO ","HttpRequestNumber":1,"HttpRequestId":"f4148f5d-2b9c-4a72-a666-bf1a33720670"}
{"@t":"2020-07-03T08:13:05.5050996Z","@mt":"{StartMessage} [Timing {TimingId}]","StartMessage":"Loading media from local cache file","TimingId":"e86913f","SourceContext":"Umbraco.Web.PublishedCache.NuCache.PublishedSnapshotService","ProcessId":19484,"ProcessName":"iisexpress","ThreadId":1,"AppDomainId":2,"AppDomainAppId":"LMW3SVC2ROOT","MachineName":"MSI","Log4NetLevel":"INFO ","HttpRequestNumber":1,"HttpRequestId":"f4148f5d-2b9c-4a72-a666-bf1a33720670"}
{"@t":"2020-07-03T08:13:05.5091019Z","@mt":"{EndMessage} ({Duration}ms) [Timing {TimingId}]","EndMessage":"Completed.","Duration":4,"TimingId":"e86913f","SourceContext":"Umbraco.Web.PublishedCache.NuCache.PublishedSnapshotService","ProcessId":19484,"ProcessName":"iisexpress","ThreadId":1,"AppDomainId":2,"AppDomainAppId":"LMW3SVC2ROOT","MachineName":"MSI","Log4NetLevel":"INFO ","HttpRequestNumber":1,"HttpRequestId":"f4148f5d-2b9c-4a72-a666-bf1a33720670"}
{"@t":"2020-07-03T08:13:05.7991007Z","@mt":"Initializing Umbraco internal event handlers for cache refreshing.","SourceContext":"Umbraco.Web.Cache.DistributedCacheBinderComponent","ProcessId":19484,"ProcessName":"iisexpress","ThreadId":1,"AppDomainId":2,"AppDomainAppId":"LMW3SVC2ROOT","MachineName":"MSI","Log4NetLevel":"INFO ","HttpRequestNumber":1,"HttpRequestId":"f4148f5d-2b9c-4a72-a666-bf1a33720670"}
{"@t":"2020-07-03T08:13:05.8611007Z","@mt":"Adding examine event handlers for {RegisteredIndexers} index providers.","RegisteredIndexers":3,"SourceContext":"Umbraco.Web.Search.ExamineComponent","ProcessId":19484,"ProcessName":"iisexpress","ThreadId":1,"AppDomainId":2,"AppDomainAppId":"LMW3SVC2ROOT","MachineName":"MSI","Log4NetLevel":"INFO ","HttpRequestNumber":1,"HttpRequestId":"f4148f5d-2b9c-4a72-a666-bf1a33720670"}
{"@t":"2020-07-03T08:13:06.0030997Z","@mt":"Starting initialize async background thread.","SourceContext":"Umbraco.Web.Search.BackgroundIndexRebuilder","ProcessId":19484,"ProcessName":"iisexpress","ThreadId":1,"AppDomainId":2,"AppDomainAppId":"LMW3SVC2ROOT","MachineName":"MSI","Log4NetLevel":"INFO ","HttpRequestNumber":1,"HttpRequestId":"f4148f5d-2b9c-4a72-a666-bf1a33720670"}
{"@t":"2020-07-03T08:13:06.0041000Z","@mt":"{EndMessage} ({Duration}ms) [Timing {TimingId}]","EndMessage":"Booted.","Duration":7531,"TimingId":"193fc46","SourceContext":"Umbraco.Core.Runtime.CoreRuntime","ProcessId":19484,"ProcessName":"iisexpress","ThreadId":1,"AppDomainId":2,"AppDomainAppId":"LMW3SVC2ROOT","MachineName":"MSI","Log4NetLevel":"INFO ","HttpRequestNumber":1,"HttpRequestId":"f4148f5d-2b9c-4a72-a666-bf1a33720670"}
{"@t":"2020-07-03T08:13:06.5411019Z","@mt":"New url {Url} detected, re-discovering application url.","Url":"http://localhost/umbraco","SourceContext":"Umbraco.Core.Sync.ApplicationUrlHelper","ProcessId":19484,"ProcessName":"iisexpress","ThreadId":10,"AppDomainId":2,"AppDomainAppId":"LMW3SVC2ROOT","MachineName":"MSI","Log4NetLevel":"INFO ","HttpRequestNumber":2,"HttpRequestId":"7c876ff7-c1a9-49b9-a4fc-b95bf4f31a80"}
{"@t":"2020-07-03T08:13:06.5431031Z","@mt":"ApplicationUrl: {UmbracoAppUrl} (UmbracoModule request)","UmbracoAppUrl":"http://localhost/umbraco","SourceContext":"Umbraco.Core.Sync.ApplicationUrlHelper","ProcessId":19484,"ProcessName":"iisexpress","ThreadId":10,"AppDomainId":2,"AppDomainAppId":"LMW3SVC2ROOT","MachineName":"MSI","Log4NetLevel":"INFO ","HttpRequestNumber":2,"HttpRequestId":"7c876ff7-c1a9-49b9-a4fc-b95bf4f31a80"}
{"@t":"2020-07-03T08:13:06.5431031Z","@mt":"ApplicationUrl: {UmbracoAppUrl} (UmbracoModule request)","UmbracoAppUrl":"http://localhost/umbraco","SourceContext":"Umbraco.Core.Sync.ApplicationUrlHelper","ProcessId":19484,"ProcessName":"iisexpress","ThreadId":9,"AppDomainId":2,"AppDomainAppId":"LMW3SVC2ROOT","MachineName":"MSI","Log4NetLevel":"INFO ","HttpRequestNumber":3,"HttpRequestId":"6efb7730-6216-4c33-9b2a-ab19e4778ea3"}
{"@t":"2020-07-03T08:14:09.8661010Z","@mt":"Missed {TypeName} Object {ObjectKey}","@l":"Warning","TypeName":"ScopeContext","ObjectKey":"857dd18f","SourceContext":"Umbraco.Core.Scoping.ScopeProvider","ProcessId":19484,"ProcessName":"iisexpress","ThreadId":12,"AppDomainId":2,"AppDomainAppId":"LMW3SVC2ROOT","MachineName":"MSI","Log4NetLevel":"WARN "}
{"@t":"2020-07-03T08:16:15.7671016Z","@mt":"Keep alive failed (at '{keepAlivePingUrl}').","@l":"Error","@x":"System.Net.Http.HttpRequestException: Wystąpił błąd podczas wysyłania żądania. ---> System.Net.WebException: Nie można połączyć się z serwerem zdalnym ---> System.Net.Sockets.SocketException: Nie można nawiązać połączenia, ponieważ komputer docelowy aktywnie go odmawia 127.0.0.1:80\r\n   w System.Net.Sockets.Socket.InternalEndConnect(IAsyncResult asyncResult)\r\n   w System.Net.Sockets.Socket.EndConnect(IAsyncResult asyncResult)\r\n   w System.Net.ServicePoint.ConnectSocketInternal(Boolean connectFailure, Socket s4, Socket s6, Socket& socket, IPAddress& address, ConnectSocketState state, IAsyncResult asyncResult, Exception& exception)\r\n   --- Koniec śladu stosu wyjątków wewnętrznych ---\r\n   w System.Net.HttpWebRequest.EndGetResponse(IAsyncResult asyncResult)\r\n   w System.Net.Http.HttpClientHandler.GetResponseCallback(IAsyncResult ar)\r\n   --- Koniec śladu stosu wyjątków wewnętrznych ---\r\n   w System.Runtime.CompilerServices.TaskAwaiter.ThrowForNonSuccess(Task task)\r\n   w System.Runtime.CompilerServices.TaskAwaiter.HandleNonSuccessAndDebuggerNotification(Task task)\r\n   w Umbraco.Web.Scheduling.KeepAlive.<PerformRunAsync>d__5.MoveNext() w d:\\a\\1\\s\\src\\Umbraco.Web\\Scheduling\\KeepAlive.cs:wiersz 69","keepAlivePingUrl":"http://localhost/umbraco/api/keepalive/ping","SourceContext":"Umbraco.Web.Scheduling.KeepAlive","ProcessId":19484,"ProcessName":"iisexpress","ThreadId":31,"AppDomainId":2,"AppDomainAppId":"LMW3SVC2ROOT","MachineName":"MSI","Log4NetLevel":"ERROR"}
{"@t":"2020-07-03T08:16:36.0501013Z","@mt":"Scheduled health check results:","SourceContext":"Umbraco.Web.HealthCheck.HealthCheckResults","ProcessId":19484,"ProcessName":"iisexpress","ThreadId":9,"AppDomainId":2,"AppDomainAppId":"LMW3SVC2ROOT","MachineName":"MSI","Log4NetLevel":"INFO "}
{"@t":"2020-07-03T08:16:36.0511027Z","@mt":"Checks for '{HealthCheckName}' all completed successfully.","HealthCheckName":"Folder & File Permissions","SourceContext":"Umbraco.Web.HealthCheck.HealthCheckResults","ProcessId":19484,"ProcessName":"iisexpress","ThreadId":9,"AppDomainId":2,"AppDomainAppId":"LMW3SVC2ROOT","MachineName":"MSI","Log4NetLevel":"INFO "}
{"@t":"2020-07-03T08:16:36.0511027Z","@mt":"Result for {HealthCheckName}: {HealthCheckResult}, Message: '{HealthCheckMessage}'","HealthCheckName":"Folder & File Permissions","HealthCheckResult":"Success","HealthCheckMessage":"Wszystkie foldery mają ustawione poprawne ustawienia.","SourceContext":"Umbraco.Web.HealthCheck.HealthCheckResults","ProcessId":19484,"ProcessName":"iisexpress","ThreadId":9,"AppDomainId":2,"AppDomainAppId":"LMW3SVC2ROOT","MachineName":"MSI","Log4NetLevel":"INFO "}
{"@t":"2020-07-03T08:16:36.0511027Z","@mt":"Result for {HealthCheckName}: {HealthCheckResult}, Message: '{HealthCheckMessage}'","HealthCheckName":"Folder & File Permissions","HealthCheckResult":"Success","HealthCheckMessage":"Wszystkie pliki mają ustawione poprawne uprawnienia.","SourceContext":"Umbraco.Web.HealthCheck.HealthCheckResults","ProcessId":19484,"ProcessName":"iisexpress","ThreadId":9,"AppDomainId":2,"AppDomainAppId":"LMW3SVC2ROOT","MachineName":"MSI","Log4NetLevel":"INFO "}
{"@t":"2020-07-03T08:16:36.0511027Z","@mt":"Checks for '{HealthCheckName}' completed with errors.","@l":"Warning","HealthCheckName":"SMTP Settings","SourceContext":"Umbraco.Web.HealthCheck.HealthCheckResults","ProcessId":19484,"ProcessName":"iisexpress","ThreadId":9,"AppDomainId":2,"AppDomainAppId":"LMW3SVC2ROOT","MachineName":"MSI","Log4NetLevel":"WARN "}
{"@t":"2020-07-03T08:16:36.0511027Z","@mt":"Result for {HealthCheckName}: {HealthCheckResult}, Message: '{HealthCheckMessage}'","HealthCheckName":"SMTP Settings","HealthCheckResult":"Error","HealthCheckMessage":"Host nie jest skonfigurowany w sekcji system.net/mailsettings pliku Web.config.","SourceContext":"Umbraco.Web.HealthCheck.HealthCheckResults","ProcessId":19484,"ProcessName":"iisexpress","ThreadId":9,"AppDomainId":2,"AppDomainAppId":"LMW3SVC2ROOT","MachineName":"MSI","Log4NetLevel":"INFO "}
{"@t":"2020-07-03T08:16:36.0511027Z","@mt":"Checks for '{HealthCheckName}' completed with errors.","@l":"Warning","HealthCheckName":"Macro errors","SourceContext":"Umbraco.Web.HealthCheck.HealthCheckResults","ProcessId":19484,"ProcessName":"iisexpress","ThreadId":9,"AppDomainId":2,"AppDomainAppId":"LMW3SVC2ROOT","MachineName":"MSI","Log4NetLevel":"WARN "}
{"@t":"2020-07-03T08:16:36.0511027Z","@mt":"Result for {HealthCheckName}: {HealthCheckResult}, Message: '{HealthCheckMessage}'","HealthCheckName":"Macro errors","HealthCheckResult":"Error","HealthCheckMessage":"MacroErrors są ustawione na 'throw' co uniemożliwi częściowe lub całkowite załadowanie stron w Twojej witrynie jeśli wystąpią jakiekolwiek błędy w makro. Korekta ustawi wartość na 'inline'.","SourceContext":"Umbraco.Web.HealthCheck.HealthCheckResults","ProcessId":19484,"ProcessName":"iisexpress","ThreadId":9,"AppDomainId":2,"AppDomainAppId":"LMW3SVC2ROOT","MachineName":"MSI","Log4NetLevel":"INFO "}
{"@t":"2020-07-03T08:16:36.0511027Z","@mt":"Checks for '{HealthCheckName}' completed with errors.","@l":"Warning","HealthCheckName":"Notification Email Settings","SourceContext":"Umbraco.Web.HealthCheck.HealthCheckResults","ProcessId":19484,"ProcessName":"iisexpress","ThreadId":9,"AppDomainId":2,"AppDomainAppId":"LMW3SVC2ROOT","MachineName":"MSI","Log4NetLevel":"WARN "}
{"@t":"2020-07-03T08:16:36.0511027Z","@mt":"Result for {HealthCheckName}: {HealthCheckResult}, Message: '{HealthCheckMessage}'","HealthCheckName":"Notification Email Settings","HealthCheckResult":"Error","HealthCheckMessage":"E-mail do powiadomień jest nadal ustawiony na domyślną wartość <strong>your@email.here</strong>.","SourceContext":"Umbraco.Web.HealthCheck.HealthCheckResults","ProcessId":19484,"ProcessName":"iisexpress","ThreadId":9,"AppDomainId":2,"AppDomainAppId":"LMW3SVC2ROOT","MachineName":"MSI","Log4NetLevel":"INFO "}
{"@t":"2020-07-03T08:16:36.0511027Z","@mt":"Checks for '{HealthCheckName}' all completed successfully.","HealthCheckName":"Try Skip IIS Custom Errors","SourceContext":"Umbraco.Web.HealthCheck.HealthCheckResults","ProcessId":19484,"ProcessName":"iisexpress","ThreadId":9,"AppDomainId":2,"AppDomainAppId":"LMW3SVC2ROOT","MachineName":"MSI","Log4NetLevel":"INFO "}
{"@t":"2020-07-03T08:16:36.0511027Z","@mt":"Result for {HealthCheckName}: {HealthCheckResult}, Message: '{HealthCheckMessage}'","HealthCheckName":"Try Skip IIS Custom Errors","HealthCheckResult":"Success","HealthCheckMessage":"Try Skip IIS Custom Errors jest ustawione na 'true' a Ty używasz IIS w wersji '10.0'.","SourceContext":"Umbraco.Web.HealthCheck.HealthCheckResults","ProcessId":19484,"ProcessName":"iisexpress","ThreadId":9,"AppDomainId":2,"AppDomainAppId":"LMW3SVC2ROOT","MachineName":"MSI","Log4NetLevel":"INFO "}
{"@t":"2020-07-03T08:16:36.0511027Z","@mt":"Checks for '{HealthCheckName}' all completed successfully.","HealthCheckName":"Custom Errors","SourceContext":"Umbraco.Web.HealthCheck.HealthCheckResults","ProcessId":19484,"ProcessName":"iisexpress","ThreadId":9,"AppDomainId":2,"AppDomainAppId":"LMW3SVC2ROOT","MachineName":"MSI","Log4NetLevel":"INFO "}
{"@t":"2020-07-03T08:16:36.0511027Z","@mt":"Result for {HealthCheckName}: {HealthCheckResult}, Message: '{HealthCheckMessage}'","HealthCheckName":"Custom Errors","HealthCheckResult":"Success","HealthCheckMessage":"Niestandardowe błędy są ustawione na 'RemoteOnly'.","SourceContext":"Umbraco.Web.HealthCheck.HealthCheckResults","ProcessId":19484,"ProcessName":"iisexpress","ThreadId":9,"AppDomainId":2,"AppDomainAppId":"LMW3SVC2ROOT","MachineName":"MSI","Log4NetLevel":"INFO "}
{"@t":"2020-07-03T08:16:36.0511027Z","@mt":"Checks for '{HealthCheckName}' all completed successfully.","HealthCheckName":"Trace Mode","SourceContext":"Umbraco.Web.HealthCheck.HealthCheckResults","ProcessId":19484,"ProcessName":"iisexpress","ThreadId":9,"AppDomainId":2,"AppDomainAppId":"LMW3SVC2ROOT","MachineName":"MSI","Log4NetLevel":"INFO "}
{"@t":"2020-07-03T08:16:36.0511027Z","@mt":"Result for {HealthCheckName}: {HealthCheckResult}, Message: '{HealthCheckMessage}'","HealthCheckName":"Trace Mode","HealthCheckResult":"Success","HealthCheckMessage":"Tryb śledzenia jest wyłączony.","SourceContext":"Umbraco.Web.HealthCheck.HealthCheckResults","ProcessId":19484,"ProcessName":"iisexpress","ThreadId":9,"AppDomainId":2,"AppDomainAppId":"LMW3SVC2ROOT","MachineName":"MSI","Log4NetLevel":"INFO "}
{"@t":"2020-07-03T08:16:36.0511027Z","@mt":"Checks for '{HealthCheckName}' completed with errors.","@l":"Warning","HealthCheckName":"Debug Compilation Mode","SourceContext":"Umbraco.Web.HealthCheck.HealthCheckResults","ProcessId":19484,"ProcessName":"iisexpress","ThreadId":9,"AppDomainId":2,"AppDomainAppId":"LMW3SVC2ROOT","MachineName":"MSI","Log4NetLevel":"WARN "}
{"@t":"2020-07-03T08:16:36.0511027Z","@mt":"Result for {HealthCheckName}: {HealthCheckResult}, Message: '{HealthCheckMessage}'","HealthCheckName":"Debug Compilation Mode","HealthCheckResult":"Error","HealthCheckMessage":"Tryb kompilacji debugowania jest obecnie włączony. Zaleca się wyłączenie tego ustawienia przed wypuszczeniem strony na produkcję.","SourceContext":"Umbraco.Web.HealthCheck.HealthCheckResults","ProcessId":19484,"ProcessName":"iisexpress","ThreadId":9,"AppDomainId":2,"AppDomainAppId":"LMW3SVC2ROOT","MachineName":"MSI","Log4NetLevel":"INFO "}
{"@t":"2020-07-03T08:16:36.0511027Z","@mt":"Checks for '{HealthCheckName}' completed with errors.","@l":"Warning","HealthCheckName":"Cross-site scripting Protection (X-XSS-Protection header)","SourceContext":"Umbraco.Web.HealthCheck.HealthCheckResults","ProcessId":19484,"ProcessName":"iisexpress","ThreadId":9,"AppDomainId":2,"AppDomainAppId":"LMW3SVC2ROOT","MachineName":"MSI","Log4NetLevel":"WARN "}
{"@t":"2020-07-03T08:16:36.0511027Z","@mt":"Result for {HealthCheckName}: {HealthCheckResult}, Message: '{HealthCheckMessage}'","HealthCheckName":"Cross-site scripting Protection (X-XSS-Protection header)","HealthCheckResult":"Error","HealthCheckMessage":"Błąd pingowania adresu URL http://localhost/umbraco - 'Nie można połączyć się z serwerem zdalnym'","SourceContext":"Umbraco.Web.HealthCheck.HealthCheckResults","ProcessId":19484,"ProcessName":"iisexpress","ThreadId":9,"AppDomainId":2,"AppDomainAppId":"LMW3SVC2ROOT","MachineName":"MSI","Log4NetLevel":"INFO "}
{"@t":"2020-07-03T08:16:36.0511027Z","@mt":"Checks for '{HealthCheckName}' completed with errors.","@l":"Warning","HealthCheckName":"Cookie hijacking and protocol downgrade attacks Protection (Strict-Transport-Security Header (HSTS))","SourceContext":"Umbraco.Web.HealthCheck.HealthCheckResults","ProcessId":19484,"ProcessName":"iisexpress","ThreadId":9,"AppDomainId":2,"AppDomainAppId":"LMW3SVC2ROOT","MachineName":"MSI","Log4NetLevel":"WARN "}
{"@t":"2020-07-03T08:16:36.0511027Z","@mt":"Result for {HealthCheckName}: {HealthCheckResult}, Message: '{HealthCheckMessage}'","HealthCheckName":"Cookie hijacking and protocol downgrade attacks Protection (Strict-Transport-Security Header (HSTS))","HealthCheckResult":"Error","HealthCheckMessage":"Błąd pingowania adresu URL http://localhost/umbraco - 'Nie można połączyć się z serwerem zdalnym'","SourceContext":"Umbraco.Web.HealthCheck.HealthCheckResults","ProcessId":19484,"ProcessName":"iisexpress","ThreadId":9,"AppDomainId":2,"AppDomainAppId":"LMW3SVC2ROOT","MachineName":"MSI","Log4NetLevel":"INFO "}
{"@t":"2020-07-03T08:16:36.0511027Z","@mt":"Checks for '{HealthCheckName}' completed with errors.","@l":"Warning","HealthCheckName":"Content/MIME Sniffing Protection","SourceContext":"Umbraco.Web.HealthCheck.HealthCheckResults","ProcessId":19484,"ProcessName":"iisexpress","ThreadId":9,"AppDomainId":2,"AppDomainAppId":"LMW3SVC2ROOT","MachineName":"MSI","Log4NetLevel":"WARN "}
{"@t":"2020-07-03T08:16:36.0511027Z","@mt":"Result for {HealthCheckName}: {HealthCheckResult}, Message: '{HealthCheckMessage}'","HealthCheckName":"Content/MIME Sniffing Protection","HealthCheckResult":"Error","HealthCheckMessage":"Błąd pingowania adresu URL http://localhost/umbraco - 'Nie można połączyć się z serwerem zdalnym'","SourceContext":"Umbraco.Web.HealthCheck.HealthCheckResults","ProcessId":19484,"ProcessName":"iisexpress","ThreadId":9,"AppDomainId":2,"AppDomainAppId":"LMW3SVC2ROOT","MachineName":"MSI","Log4NetLevel":"INFO "}
{"@t":"2020-07-03T08:16:36.0511027Z","@mt":"Checks for '{HealthCheckName}' completed with errors.","@l":"Warning","HealthCheckName":"Excessive Headers","SourceContext":"Umbraco.Web.HealthCheck.HealthCheckResults","ProcessId":19484,"ProcessName":"iisexpress","ThreadId":9,"AppDomainId":2,"AppDomainAppId":"LMW3SVC2ROOT","MachineName":"MSI","Log4NetLevel":"WARN "}
{"@t":"2020-07-03T08:16:36.0511027Z","@mt":"Result for {HealthCheckName}: {HealthCheckResult}, Message: '{HealthCheckMessage}'","HealthCheckName":"Excessive Headers","HealthCheckResult":"Warning","HealthCheckMessage":"[httpsCheckInvalidUrl]","SourceContext":"Umbraco.Web.HealthCheck.HealthCheckResults","ProcessId":19484,"ProcessName":"iisexpress","ThreadId":9,"AppDomainId":2,"AppDomainAppId":"LMW3SVC2ROOT","MachineName":"MSI","Log4NetLevel":"INFO "}
{"@t":"2020-07-03T08:16:36.0511027Z","@mt":"Checks for '{HealthCheckName}' completed with errors.","@l":"Warning","HealthCheckName":"Click-Jacking Protection","SourceContext":"Umbraco.Web.HealthCheck.HealthCheckResults","ProcessId":19484,"ProcessName":"iisexpress","ThreadId":9,"AppDomainId":2,"AppDomainAppId":"LMW3SVC2ROOT","MachineName":"MSI","Log4NetLevel":"WARN "}
{"@t":"2020-07-03T08:16:36.0511027Z","@mt":"Result for {HealthCheckName}: {HealthCheckResult}, Message: '{HealthCheckMessage}'","HealthCheckName":"Click-Jacking Protection","HealthCheckResult":"Error","HealthCheckMessage":"Błąd pingowania adresu URL http://localhost/umbraco - 'Nie można połączyć się z serwerem zdalnym'","SourceContext":"Umbraco.Web.HealthCheck.HealthCheckResults","ProcessId":19484,"ProcessName":"iisexpress","ThreadId":9,"AppDomainId":2,"AppDomainAppId":"LMW3SVC2ROOT","MachineName":"MSI","Log4NetLevel":"INFO "}
{"@t":"2020-07-03T08:16:36.0511027Z","@mt":"Checks for '{HealthCheckName}' completed with errors.","@l":"Warning","HealthCheckName":"HTTPS Configuration","SourceContext":"Umbraco.Web.HealthCheck.HealthCheckResults","ProcessId":19484,"ProcessName":"iisexpress","ThreadId":9,"AppDomainId":2,"AppDomainAppId":"LMW3SVC2ROOT","MachineName":"MSI","Log4NetLevel":"WARN "}
{"@t":"2020-07-03T08:16:36.0511027Z","@mt":"Result for {HealthCheckName}: {HealthCheckResult}, Message: '{HealthCheckMessage}'","HealthCheckName":"HTTPS Configuration","HealthCheckResult":"Error","HealthCheckMessage":"Oglądasz not stronę używając HTTPS.","SourceContext":"Umbraco.Web.HealthCheck.HealthCheckResults","ProcessId":19484,"ProcessName":"iisexpress","ThreadId":9,"AppDomainId":2,"AppDomainAppId":"LMW3SVC2ROOT","MachineName":"MSI","Log4NetLevel":"INFO "}
{"@t":"2020-07-03T08:16:36.0511027Z","@mt":"Result for {HealthCheckName}: {HealthCheckResult}, Message: '{HealthCheckMessage}'","HealthCheckName":"HTTPS Configuration","HealthCheckResult":"Info","HealthCheckMessage":"appSetting 'Umbraco.Core.UseHttps' został ustawiony na 'false' w Twoim pliku web.config. Po uzyskaniu dostępu do strony, używając HTTPS, powinieneś go ustawić na 'true'.","SourceContext":"Umbraco.Web.HealthCheck.HealthCheckResults","ProcessId":19484,"ProcessName":"iisexpress","ThreadId":9,"AppDomainId":2,"AppDomainAppId":"LMW3SVC2ROOT","MachineName":"MSI","Log4NetLevel":"INFO "}
{"@t":"2020-07-03T08:16:36.0511027Z","@mt":"Result for {HealthCheckName}: {HealthCheckResult}, Message: '{HealthCheckMessage}'","HealthCheckName":"HTTPS Configuration","HealthCheckResult":"Error","HealthCheckMessage":"Błąd pingowania adresu URL https://localhost/umbraco - 'Nie można połączyć się z serwerem zdalnym'","SourceContext":"Umbraco.Web.HealthCheck.HealthCheckResults","ProcessId":19484,"ProcessName":"iisexpress","ThreadId":9,"AppDomainId":2,"AppDomainAppId":"LMW3SVC2ROOT","MachineName":"MSI","Log4NetLevel":"INFO "}
{"@t":"2020-07-03T08:21:19.8311616Z","@mt":"Keep alive failed (at '{keepAlivePingUrl}').","@l":"Error","@x":"System.Net.Http.HttpRequestException: Wystąpił błąd podczas wysyłania żądania. ---> System.Net.WebException: Nie można połączyć się z serwerem zdalnym ---> System.Net.Sockets.SocketException: Nie można nawiązać połączenia, ponieważ komputer docelowy aktywnie go odmawia 127.0.0.1:80\r\n   w System.Net.Sockets.Socket.InternalEndConnect(IAsyncResult asyncResult)\r\n   w System.Net.Sockets.Socket.EndConnect(IAsyncResult asyncResult)\r\n   w System.Net.ServicePoint.ConnectSocketInternal(Boolean connectFailure, Socket s4, Socket s6, Socket& socket, IPAddress& address, ConnectSocketState state, IAsyncResult asyncResult, Exception& exception)\r\n   --- Koniec śladu stosu wyjątków wewnętrznych ---\r\n   w System.Net.HttpWebRequest.EndGetResponse(IAsyncResult asyncResult)\r\n   w System.Net.Http.HttpClientHandler.GetResponseCallback(IAsyncResult ar)\r\n   --- Koniec śladu stosu wyjątków wewnętrznych ---\r\n   w System.Runtime.CompilerServices.TaskAwaiter.ThrowForNonSuccess(Task task)\r\n   w System.Runtime.CompilerServices.TaskAwaiter.HandleNonSuccessAndDebuggerNotification(Task task)\r\n   w Umbraco.Web.Scheduling.KeepAlive.<PerformRunAsync>d__5.MoveNext() w d:\\a\\1\\s\\src\\Umbraco.Web\\Scheduling\\KeepAlive.cs:wiersz 69","keepAlivePingUrl":"http://localhost/umbraco/api/keepalive/ping","SourceContext":"Umbraco.Web.Scheduling.KeepAlive","ProcessId":19484,"ProcessName":"iisexpress","ThreadId":32,"AppDomainId":2,"AppDomainAppId":"LMW3SVC2ROOT","MachineName":"MSI","Log4NetLevel":"ERROR"}
{"@t":"2020-07-03T13:32:03.4519855Z","@mt":"{StartMessage} [Timing {TimingId}]","StartMessage":"Booting Umbraco 8.6.3.","TimingId":"68f0b94","SourceContext":"Umbraco.Core.Runtime.CoreRuntime","ProcessId":11588,"ProcessName":"iisexpress","ThreadId":1,"AppDomainId":2,"AppDomainAppId":"LMW3SVC2ROOT","MachineName":"MSI","Log4NetLevel":"INFO ","HttpRequestNumber":1,"HttpRequestId":"f0ea5a2b-6e46-4614-a14d-e3a4028050dc"}
{"@t":"2020-07-03T13:32:03.4779853Z","@mt":"Booting site '{HostingSiteName}', app '{HostingApplicationID}', path '{HostingPhysicalPath}', server '{MachineName}'.","HostingSiteName":"Emi-Center","HostingApplicationID":"/LM/W3SVC/2/ROOT","HostingPhysicalPath":"C:\\Users\\pisaq\\source\\repos\\Emi-Center\\","MachineName":"MSI","SourceContext":"Umbraco.Core.Runtime.CoreRuntime","ProcessId":11588,"ProcessName":"iisexpress","ThreadId":1,"AppDomainId":2,"AppDomainAppId":"LMW3SVC2ROOT","Log4NetLevel":"INFO ","HttpRequestNumber":1,"HttpRequestId":"f0ea5a2b-6e46-4614-a14d-e3a4028050dc"}
{"@t":"2020-07-03T13:32:10.4709878Z","@mt":"{FailMessage} ({Duration}ms) [Timing {TimingId}]","@l":"Error","@x":"Umbraco.Core.Exceptions.BootFailedException: Boot failed. ---> System.Configuration.ConfigurationErrorsException: Nieznany atrybut 'key'. Pamiętaj, że w nazwach atrybutów jest uwzględniana wielkość liter. (C:\\Users\\pisaq\\source\\repos\\Emi-Center\\web.config line 49)\r\n   w System.Configuration.BaseConfigurationRecord.EvaluateOne(String[] keys, SectionInput input, Boolean isTrusted, FactoryRecord factoryRecord, SectionRecord sectionRecord, Object parentResult)\r\n   w System.Configuration.BaseConfigurationRecord.Evaluate(FactoryRecord factoryRecord, SectionRecord sectionRecord, Object parentResult, Boolean getLkg, Boolean getRuntimeObject, Object& result, Object& resultRuntimeObject)\r\n   w System.Configuration.BaseConfigurationRecord.GetSectionRecursive(String configKey, Boolean getLkg, Boolean checkPermission, Boolean getRuntimeObject, Boolean requestIsHere, Object& result, Object& resultRuntimeObject)\r\n   w System.Configuration.BaseConfigurationRecord.GetSection(String configKey)\r\n   w System.Web.HttpContext.GetSection(String sectionName)\r\n   w System.Web.Configuration.HttpConfigurationSystem.GetSection(String sectionName)\r\n   w System.Web.Configuration.HttpConfigurationSystem.System.Configuration.Internal.IInternalConfigSystem.GetSection(String configKey)\r\n   w System.Configuration.ConfigurationManager.GetSection(String sectionName)\r\n   w System.Configuration.ConfigurationManager.get_ConnectionStrings()\r\n   w Umbraco.Core.Persistence.UmbracoDatabaseFactory..ctor(String connectionStringName, ILogger logger, Lazy`1 mappers) w d:\\a\\1\\s\\src\\Umbraco.Core\\Persistence\\UmbracoDatabaseFactory.cs:wiersz 67\r\n   w Umbraco.Core.Runtime.CoreRuntime.GetDatabaseFactory() w d:\\a\\1\\s\\src\\Umbraco.Core\\Runtime\\CoreRuntime.cs:wiersz 370\r\n   w Umbraco.Core.Runtime.CoreRuntime.Boot(IRegister register, DisposableTimer timer) w d:\\a\\1\\s\\src\\Umbraco.Core\\Runtime\\CoreRuntime.cs:wiersz 128\r\n   --- Koniec śladu stosu wyjątków wewnętrznych ---","FailMessage":"Boot failed.","Duration":7027,"TimingId":"68f0b94","SourceContext":"Umbraco.Core.Runtime.CoreRuntime","ProcessId":11588,"ProcessName":"iisexpress","ThreadId":1,"AppDomainId":2,"AppDomainAppId":"LMW3SVC2ROOT","MachineName":"MSI","Log4NetLevel":"ERROR","HttpRequestNumber":1,"HttpRequestId":"f0ea5a2b-6e46-4614-a14d-e3a4028050dc"}
{"@t":"2020-07-03T13:32:40.8919883Z","@mt":"{StartMessage} [Timing {TimingId}]","StartMessage":"Booting Umbraco 8.6.3.","TimingId":"28cc923","SourceContext":"Umbraco.Core.Runtime.CoreRuntime","ProcessId":9240,"ProcessName":"iisexpress","ThreadId":1,"AppDomainId":2,"AppDomainAppId":"LMW3SVC2ROOT","MachineName":"MSI","Log4NetLevel":"INFO ","HttpRequestNumber":1,"HttpRequestId":"9ec99aa3-3e54-47d9-ad24-d13c635267f8"}
{"@t":"2020-07-03T13:32:40.9189869Z","@mt":"Booting site '{HostingSiteName}', app '{HostingApplicationID}', path '{HostingPhysicalPath}', server '{MachineName}'.","HostingSiteName":"Emi-Center","HostingApplicationID":"/LM/W3SVC/2/ROOT","HostingPhysicalPath":"C:\\Users\\pisaq\\source\\repos\\Emi-Center\\","MachineName":"MSI","SourceContext":"Umbraco.Core.Runtime.CoreRuntime","ProcessId":9240,"ProcessName":"iisexpress","ThreadId":1,"AppDomainId":2,"AppDomainAppId":"LMW3SVC2ROOT","Log4NetLevel":"INFO ","HttpRequestNumber":1,"HttpRequestId":"9ec99aa3-3e54-47d9-ad24-d13c635267f8"}
{"@t":"2020-07-03T13:32:49.5249890Z","@mt":"{FailMessage} ({Duration}ms) [Timing {TimingId}]","@l":"Error","@x":"Umbraco.Core.Exceptions.BootFailedException: Boot failed. ---> System.Configuration.ConfigurationErrorsException: Nieznany atrybut 'key'. Pamiętaj, że w nazwach atrybutów jest uwzględniana wielkość liter. (C:\\Users\\pisaq\\source\\repos\\Emi-Center\\web.config line 49)\r\n   w System.Configuration.BaseConfigurationRecord.EvaluateOne(String[] keys, SectionInput input, Boolean isTrusted, FactoryRecord factoryRecord, SectionRecord sectionRecord, Object parentResult)\r\n   w System.Configuration.BaseConfigurationRecord.Evaluate(FactoryRecord factoryRecord, SectionRecord sectionRecord, Object parentResult, Boolean getLkg, Boolean getRuntimeObject, Object& result, Object& resultRuntimeObject)\r\n   w System.Configuration.BaseConfigurationRecord.GetSectionRecursive(String configKey, Boolean getLkg, Boolean checkPermission, Boolean getRuntimeObject, Boolean requestIsHere, Object& result, Object& resultRuntimeObject)\r\n   w System.Configuration.BaseConfigurationRecord.GetSection(String configKey)\r\n   w System.Web.HttpContext.GetSection(String sectionName)\r\n   w System.Web.Configuration.HttpConfigurationSystem.GetSection(String sectionName)\r\n   w System.Web.Configuration.HttpConfigurationSystem.System.Configuration.Internal.IInternalConfigSystem.GetSection(String configKey)\r\n   w System.Configuration.ConfigurationManager.GetSection(String sectionName)\r\n   w System.Configuration.ConfigurationManager.get_ConnectionStrings()\r\n   w Umbraco.Core.Persistence.UmbracoDatabaseFactory..ctor(String connectionStringName, ILogger logger, Lazy`1 mappers) w d:\\a\\1\\s\\src\\Umbraco.Core\\Persistence\\UmbracoDatabaseFactory.cs:wiersz 67\r\n   w Umbraco.Core.Runtime.CoreRuntime.GetDatabaseFactory() w d:\\a\\1\\s\\src\\Umbraco.Core\\Runtime\\CoreRuntime.cs:wiersz 370\r\n   w Umbraco.Core.Runtime.CoreRuntime.Boot(IRegister register, DisposableTimer timer) w d:\\a\\1\\s\\src\\Umbraco.Core\\Runtime\\CoreRuntime.cs:wiersz 128\r\n   --- Koniec śladu stosu wyjątków wewnętrznych ---","FailMessage":"Boot failed.","Duration":8641,"TimingId":"28cc923","SourceContext":"Umbraco.Core.Runtime.CoreRuntime","ProcessId":9240,"ProcessName":"iisexpress","ThreadId":1,"AppDomainId":2,"AppDomainAppId":"LMW3SVC2ROOT","MachineName":"MSI","Log4NetLevel":"ERROR","HttpRequestNumber":1,"HttpRequestId":"9ec99aa3-3e54-47d9-ad24-d13c635267f8"}
{"@t":"2020-07-03T13:38:25.6149876Z","@mt":"{StartMessage} [Timing {TimingId}]","StartMessage":"Booting Umbraco 8.6.3.","TimingId":"e74d23f","SourceContext":"Umbraco.Core.Runtime.CoreRuntime","ProcessId":9884,"ProcessName":"iisexpress","ThreadId":1,"AppDomainId":2,"AppDomainAppId":"LMW3SVC2ROOT","MachineName":"MSI","Log4NetLevel":"INFO ","HttpRequestNumber":1,"HttpRequestId":"69bf67d1-a4ea-4207-8b56-c29b4cbb77b9"}
{"@t":"2020-07-03T13:38:25.6439901Z","@mt":"Booting site '{HostingSiteName}', app '{HostingApplicationID}', path '{HostingPhysicalPath}', server '{MachineName}'.","HostingSiteName":"Emi-Center","HostingApplicationID":"/LM/W3SVC/2/ROOT","HostingPhysicalPath":"C:\\Users\\pisaq\\source\\repos\\Emi-Center\\","MachineName":"MSI","SourceContext":"Umbraco.Core.Runtime.CoreRuntime","ProcessId":9884,"ProcessName":"iisexpress","ThreadId":1,"AppDomainId":2,"AppDomainAppId":"LMW3SVC2ROOT","Log4NetLevel":"INFO ","HttpRequestNumber":1,"HttpRequestId":"69bf67d1-a4ea-4207-8b56-c29b4cbb77b9"}
{"@t":"2020-07-03T13:38:25.9259897Z","@mt":"Acquiring.","SourceContext":"Umbraco.Core.Runtime.MainDom","ProcessId":9884,"ProcessName":"iisexpress","ThreadId":1,"AppDomainId":2,"AppDomainAppId":"LMW3SVC2ROOT","MachineName":"MSI","Log4NetLevel":"INFO ","HttpRequestNumber":1,"HttpRequestId":"69bf67d1-a4ea-4207-8b56-c29b4cbb77b9"}
{"@t":"2020-07-03T13:38:25.9279912Z","@mt":"Acquired.","SourceContext":"Umbraco.Core.Runtime.MainDom","ProcessId":9884,"ProcessName":"iisexpress","ThreadId":1,"AppDomainId":2,"AppDomainAppId":"LMW3SVC2ROOT","MachineName":"MSI","Log4NetLevel":"INFO ","HttpRequestNumber":1,"HttpRequestId":"69bf67d1-a4ea-4207-8b56-c29b4cbb77b9"}
{"@t":"2020-07-03T13:38:27.0969865Z","@mt":"{StartMessage} [Timing {TimingId}]","StartMessage":"Resolving composer types.","TimingId":"41247cb","SourceContext":"Umbraco.Core.Runtime.CoreRuntime","ProcessId":9884,"ProcessName":"iisexpress","ThreadId":1,"AppDomainId":2,"AppDomainAppId":"LMW3SVC2ROOT","MachineName":"MSI","Log4NetLevel":"INFO ","HttpRequestNumber":1,"HttpRequestId":"69bf67d1-a4ea-4207-8b56-c29b4cbb77b9"}
{"@t":"2020-07-03T13:38:27.3479870Z","@mt":"{EndMessage} ({Duration}ms) [Timing {TimingId}]","EndMessage":"Resolved.","Duration":249,"TimingId":"41247cb","SourceContext":"Umbraco.Core.Runtime.CoreRuntime","ProcessId":9884,"ProcessName":"iisexpress","ThreadId":1,"AppDomainId":2,"AppDomainAppId":"LMW3SVC2ROOT","MachineName":"MSI","Log4NetLevel":"INFO ","HttpRequestNumber":1,"HttpRequestId":"69bf67d1-a4ea-4207-8b56-c29b4cbb77b9"}
{"@t":"2020-07-03T13:38:28.2459902Z","@mt":"Registered with MainDom, localContentDbExists? {LocalContentDbExists}, localMediaDbExists? {LocalMediaDbExists}","LocalContentDbExists":true,"LocalMediaDbExists":true,"SourceContext":"Umbraco.Web.PublishedCache.NuCache.PublishedSnapshotService","ProcessId":9884,"ProcessName":"iisexpress","ThreadId":1,"AppDomainId":2,"AppDomainAppId":"LMW3SVC2ROOT","MachineName":"MSI","Log4NetLevel":"INFO ","HttpRequestNumber":1,"HttpRequestId":"69bf67d1-a4ea-4207-8b56-c29b4cbb77b9"}
{"@t":"2020-07-03T13:38:28.2459902Z","@mt":"Creating the content store, localContentDbExists? {LocalContentDbExists}","LocalContentDbExists":true,"SourceContext":"Umbraco.Web.PublishedCache.NuCache.PublishedSnapshotService","ProcessId":9884,"ProcessName":"iisexpress","ThreadId":1,"AppDomainId":2,"AppDomainAppId":"LMW3SVC2ROOT","MachineName":"MSI","Log4NetLevel":"INFO ","HttpRequestNumber":1,"HttpRequestId":"69bf67d1-a4ea-4207-8b56-c29b4cbb77b9"}
{"@t":"2020-07-03T13:38:28.2529887Z","@mt":"Creating the media store, localMediaDbExists? {LocalMediaDbExists}","LocalMediaDbExists":true,"SourceContext":"Umbraco.Web.PublishedCache.NuCache.PublishedSnapshotService","ProcessId":9884,"ProcessName":"iisexpress","ThreadId":1,"AppDomainId":2,"AppDomainAppId":"LMW3SVC2ROOT","MachineName":"MSI","Log4NetLevel":"INFO ","HttpRequestNumber":1,"HttpRequestId":"69bf67d1-a4ea-4207-8b56-c29b4cbb77b9"}
{"@t":"2020-07-03T13:38:28.9509895Z","@mt":"{StartMessage} [Timing {TimingId}]","StartMessage":"Loading content from local cache file","TimingId":"6e1b71e","SourceContext":"Umbraco.Web.PublishedCache.NuCache.PublishedSnapshotService","ProcessId":9884,"ProcessName":"iisexpress","ThreadId":1,"AppDomainId":2,"AppDomainAppId":"LMW3SVC2ROOT","MachineName":"MSI","Log4NetLevel":"INFO ","HttpRequestNumber":1,"HttpRequestId":"69bf67d1-a4ea-4207-8b56-c29b4cbb77b9"}
{"@t":"2020-07-03T13:38:28.9849852Z","@mt":"{EndMessage} ({Duration}ms) [Timing {TimingId}]","EndMessage":"Completed.","Duration":33,"TimingId":"6e1b71e","SourceContext":"Umbraco.Web.PublishedCache.NuCache.PublishedSnapshotService","ProcessId":9884,"ProcessName":"iisexpress","ThreadId":1,"AppDomainId":2,"AppDomainAppId":"LMW3SVC2ROOT","MachineName":"MSI","Log4NetLevel":"INFO ","HttpRequestNumber":1,"HttpRequestId":"69bf67d1-a4ea-4207-8b56-c29b4cbb77b9"}
{"@t":"2020-07-03T13:38:29.0609861Z","@mt":"{StartMessage} [Timing {TimingId}]","StartMessage":"Loading media from local cache file","TimingId":"ab4afcd","SourceContext":"Umbraco.Web.PublishedCache.NuCache.PublishedSnapshotService","ProcessId":9884,"ProcessName":"iisexpress","ThreadId":1,"AppDomainId":2,"AppDomainAppId":"LMW3SVC2ROOT","MachineName":"MSI","Log4NetLevel":"INFO ","HttpRequestNumber":1,"HttpRequestId":"69bf67d1-a4ea-4207-8b56-c29b4cbb77b9"}
{"@t":"2020-07-03T13:38:29.0639881Z","@mt":"{EndMessage} ({Duration}ms) [Timing {TimingId}]","EndMessage":"Completed.","Duration":3,"TimingId":"ab4afcd","SourceContext":"Umbraco.Web.PublishedCache.NuCache.PublishedSnapshotService","ProcessId":9884,"ProcessName":"iisexpress","ThreadId":1,"AppDomainId":2,"AppDomainAppId":"LMW3SVC2ROOT","MachineName":"MSI","Log4NetLevel":"INFO ","HttpRequestNumber":1,"HttpRequestId":"69bf67d1-a4ea-4207-8b56-c29b4cbb77b9"}
{"@t":"2020-07-03T13:38:29.3899874Z","@mt":"Initializing Umbraco internal event handlers for cache refreshing.","SourceContext":"Umbraco.Web.Cache.DistributedCacheBinderComponent","ProcessId":9884,"ProcessName":"iisexpress","ThreadId":1,"AppDomainId":2,"AppDomainAppId":"LMW3SVC2ROOT","MachineName":"MSI","Log4NetLevel":"INFO ","HttpRequestNumber":1,"HttpRequestId":"69bf67d1-a4ea-4207-8b56-c29b4cbb77b9"}
{"@t":"2020-07-03T13:38:29.4459875Z","@mt":"Adding examine event handlers for {RegisteredIndexers} index providers.","RegisteredIndexers":3,"SourceContext":"Umbraco.Web.Search.ExamineComponent","ProcessId":9884,"ProcessName":"iisexpress","ThreadId":1,"AppDomainId":2,"AppDomainAppId":"LMW3SVC2ROOT","MachineName":"MSI","Log4NetLevel":"INFO ","HttpRequestNumber":1,"HttpRequestId":"69bf67d1-a4ea-4207-8b56-c29b4cbb77b9"}
{"@t":"2020-07-03T13:38:29.5899866Z","@mt":"Forcing index {IndexerName} to be unlocked since it was left in a locked state","IndexerName":"InternalIndex","SourceContext":"Umbraco.Examine.ExamineExtensions","ProcessId":9884,"ProcessName":"iisexpress","ThreadId":1,"AppDomainId":2,"AppDomainAppId":"LMW3SVC2ROOT","MachineName":"MSI","Log4NetLevel":"INFO ","HttpRequestNumber":1,"HttpRequestId":"69bf67d1-a4ea-4207-8b56-c29b4cbb77b9"}
{"@t":"2020-07-03T13:38:29.5909856Z","@mt":"Forcing index {IndexerName} to be unlocked since it was left in a locked state","IndexerName":"MembersIndex","SourceContext":"Umbraco.Examine.ExamineExtensions","ProcessId":9884,"ProcessName":"iisexpress","ThreadId":1,"AppDomainId":2,"AppDomainAppId":"LMW3SVC2ROOT","MachineName":"MSI","Log4NetLevel":"INFO ","HttpRequestNumber":1,"HttpRequestId":"69bf67d1-a4ea-4207-8b56-c29b4cbb77b9"}
{"@t":"2020-07-03T13:38:29.5909856Z","@mt":"Forcing index {IndexerName} to be unlocked since it was left in a locked state","IndexerName":"ExternalIndex","SourceContext":"Umbraco.Examine.ExamineExtensions","ProcessId":9884,"ProcessName":"iisexpress","ThreadId":1,"AppDomainId":2,"AppDomainAppId":"LMW3SVC2ROOT","MachineName":"MSI","Log4NetLevel":"INFO ","HttpRequestNumber":1,"HttpRequestId":"69bf67d1-a4ea-4207-8b56-c29b4cbb77b9"}
{"@t":"2020-07-03T13:38:29.5929886Z","@mt":"Starting initialize async background thread.","SourceContext":"Umbraco.Web.Search.BackgroundIndexRebuilder","ProcessId":9884,"ProcessName":"iisexpress","ThreadId":1,"AppDomainId":2,"AppDomainAppId":"LMW3SVC2ROOT","MachineName":"MSI","Log4NetLevel":"INFO ","HttpRequestNumber":1,"HttpRequestId":"69bf67d1-a4ea-4207-8b56-c29b4cbb77b9"}
{"@t":"2020-07-03T13:38:29.5939877Z","@mt":"{EndMessage} ({Duration}ms) [Timing {TimingId}]","EndMessage":"Booted.","Duration":3989,"TimingId":"e74d23f","SourceContext":"Umbraco.Core.Runtime.CoreRuntime","ProcessId":9884,"ProcessName":"iisexpress","ThreadId":1,"AppDomainId":2,"AppDomainAppId":"LMW3SVC2ROOT","MachineName":"MSI","Log4NetLevel":"INFO ","HttpRequestNumber":1,"HttpRequestId":"69bf67d1-a4ea-4207-8b56-c29b4cbb77b9"}
{"@t":"2020-07-03T13:38:30.0749846Z","@mt":"New url {Url} detected, re-discovering application url.","Url":"http://localhost/umbraco","SourceContext":"Umbraco.Core.Sync.ApplicationUrlHelper","ProcessId":9884,"ProcessName":"iisexpress","ThreadId":5,"AppDomainId":2,"AppDomainAppId":"LMW3SVC2ROOT","MachineName":"MSI","Log4NetLevel":"INFO ","HttpRequestNumber":2,"HttpRequestId":"9007a118-d6f1-4321-832c-a00ea5ba709e"}
{"@t":"2020-07-03T13:38:30.0769896Z","@mt":"ApplicationUrl: {UmbracoAppUrl} (UmbracoModule request)","UmbracoAppUrl":"http://localhost/umbraco","SourceContext":"Umbraco.Core.Sync.ApplicationUrlHelper","ProcessId":9884,"ProcessName":"iisexpress","ThreadId":5,"AppDomainId":2,"AppDomainAppId":"LMW3SVC2ROOT","MachineName":"MSI","Log4NetLevel":"INFO ","HttpRequestNumber":2,"HttpRequestId":"9007a118-d6f1-4321-832c-a00ea5ba709e"}
{"@t":"2020-07-03T13:39:40.1889877Z","@mt":"{StartMessage} [Timing {TimingId}]","StartMessage":"Booting Umbraco 8.6.3.","TimingId":"4fb706a","SourceContext":"Umbraco.Core.Runtime.CoreRuntime","ProcessId":19316,"ProcessName":"iisexpress","ThreadId":1,"AppDomainId":2,"AppDomainAppId":"LMW3SVC2ROOT","MachineName":"MSI","Log4NetLevel":"INFO ","HttpRequestNumber":1,"HttpRequestId":"9ab0fc0c-17e7-4013-86fd-df8ec195ffdf"}
{"@t":"2020-07-03T13:39:40.2149871Z","@mt":"Booting site '{HostingSiteName}', app '{HostingApplicationID}', path '{HostingPhysicalPath}', server '{MachineName}'.","HostingSiteName":"Emi-Center","HostingApplicationID":"/LM/W3SVC/2/ROOT","HostingPhysicalPath":"C:\\Users\\pisaq\\source\\repos\\Emi-Center\\","MachineName":"MSI","SourceContext":"Umbraco.Core.Runtime.CoreRuntime","ProcessId":19316,"ProcessName":"iisexpress","ThreadId":1,"AppDomainId":2,"AppDomainAppId":"LMW3SVC2ROOT","Log4NetLevel":"INFO ","HttpRequestNumber":1,"HttpRequestId":"9ab0fc0c-17e7-4013-86fd-df8ec195ffdf"}
{"@t":"2020-07-03T13:39:40.4069896Z","@mt":"Acquiring.","SourceContext":"Umbraco.Core.Runtime.MainDom","ProcessId":19316,"ProcessName":"iisexpress","ThreadId":1,"AppDomainId":2,"AppDomainAppId":"LMW3SVC2ROOT","MachineName":"MSI","Log4NetLevel":"INFO ","HttpRequestNumber":1,"HttpRequestId":"9ab0fc0c-17e7-4013-86fd-df8ec195ffdf"}
{"@t":"2020-07-03T13:39:40.4089905Z","@mt":"Acquired.","SourceContext":"Umbraco.Core.Runtime.MainDom","ProcessId":19316,"ProcessName":"iisexpress","ThreadId":1,"AppDomainId":2,"AppDomainAppId":"LMW3SVC2ROOT","MachineName":"MSI","Log4NetLevel":"INFO ","HttpRequestNumber":1,"HttpRequestId":"9ab0fc0c-17e7-4013-86fd-df8ec195ffdf"}
{"@t":"2020-07-03T13:39:41.3099856Z","@mt":"{StartMessage} [Timing {TimingId}]","StartMessage":"Resolving composer types.","TimingId":"75dcf07","SourceContext":"Umbraco.Core.Runtime.CoreRuntime","ProcessId":19316,"ProcessName":"iisexpress","ThreadId":1,"AppDomainId":2,"AppDomainAppId":"LMW3SVC2ROOT","MachineName":"MSI","Log4NetLevel":"INFO ","HttpRequestNumber":1,"HttpRequestId":"9ab0fc0c-17e7-4013-86fd-df8ec195ffdf"}
{"@t":"2020-07-03T13:39:41.5609878Z","@mt":"{EndMessage} ({Duration}ms) [Timing {TimingId}]","EndMessage":"Resolved.","Duration":249,"TimingId":"75dcf07","SourceContext":"Umbraco.Core.Runtime.CoreRuntime","ProcessId":19316,"ProcessName":"iisexpress","ThreadId":1,"AppDomainId":2,"AppDomainAppId":"LMW3SVC2ROOT","MachineName":"MSI","Log4NetLevel":"INFO ","HttpRequestNumber":1,"HttpRequestId":"9ab0fc0c-17e7-4013-86fd-df8ec195ffdf"}
{"@t":"2020-07-03T13:39:42.3239857Z","@mt":"Registered with MainDom, localContentDbExists? {LocalContentDbExists}, localMediaDbExists? {LocalMediaDbExists}","LocalContentDbExists":true,"LocalMediaDbExists":true,"SourceContext":"Umbraco.Web.PublishedCache.NuCache.PublishedSnapshotService","ProcessId":19316,"ProcessName":"iisexpress","ThreadId":1,"AppDomainId":2,"AppDomainAppId":"LMW3SVC2ROOT","MachineName":"MSI","Log4NetLevel":"INFO ","HttpRequestNumber":1,"HttpRequestId":"9ab0fc0c-17e7-4013-86fd-df8ec195ffdf"}
{"@t":"2020-07-03T13:39:42.3239857Z","@mt":"Creating the content store, localContentDbExists? {LocalContentDbExists}","LocalContentDbExists":true,"SourceContext":"Umbraco.Web.PublishedCache.NuCache.PublishedSnapshotService","ProcessId":19316,"ProcessName":"iisexpress","ThreadId":1,"AppDomainId":2,"AppDomainAppId":"LMW3SVC2ROOT","MachineName":"MSI","Log4NetLevel":"INFO ","HttpRequestNumber":1,"HttpRequestId":"9ab0fc0c-17e7-4013-86fd-df8ec195ffdf"}
{"@t":"2020-07-03T13:39:42.3259877Z","@mt":"Creating the media store, localMediaDbExists? {LocalMediaDbExists}","LocalMediaDbExists":true,"SourceContext":"Umbraco.Web.PublishedCache.NuCache.PublishedSnapshotService","ProcessId":19316,"ProcessName":"iisexpress","ThreadId":1,"AppDomainId":2,"AppDomainAppId":"LMW3SVC2ROOT","MachineName":"MSI","Log4NetLevel":"INFO ","HttpRequestNumber":1,"HttpRequestId":"9ab0fc0c-17e7-4013-86fd-df8ec195ffdf"}
{"@t":"2020-07-03T13:39:42.8639905Z","@mt":"{StartMessage} [Timing {TimingId}]","StartMessage":"Loading content from local cache file","TimingId":"92a3b2b","SourceContext":"Umbraco.Web.PublishedCache.NuCache.PublishedSnapshotService","ProcessId":19316,"ProcessName":"iisexpress","ThreadId":1,"AppDomainId":2,"AppDomainAppId":"LMW3SVC2ROOT","MachineName":"MSI","Log4NetLevel":"INFO ","HttpRequestNumber":1,"HttpRequestId":"9ab0fc0c-17e7-4013-86fd-df8ec195ffdf"}
{"@t":"2020-07-03T13:39:42.8959875Z","@mt":"{EndMessage} ({Duration}ms) [Timing {TimingId}]","EndMessage":"Completed.","Duration":31,"TimingId":"92a3b2b","SourceContext":"Umbraco.Web.PublishedCache.NuCache.PublishedSnapshotService","ProcessId":19316,"ProcessName":"iisexpress","ThreadId":1,"AppDomainId":2,"AppDomainAppId":"LMW3SVC2ROOT","MachineName":"MSI","Log4NetLevel":"INFO ","HttpRequestNumber":1,"HttpRequestId":"9ab0fc0c-17e7-4013-86fd-df8ec195ffdf"}
{"@t":"2020-07-03T13:39:42.9719878Z","@mt":"{StartMessage} [Timing {TimingId}]","StartMessage":"Loading media from local cache file","TimingId":"1e68c54","SourceContext":"Umbraco.Web.PublishedCache.NuCache.PublishedSnapshotService","ProcessId":19316,"ProcessName":"iisexpress","ThreadId":1,"AppDomainId":2,"AppDomainAppId":"LMW3SVC2ROOT","MachineName":"MSI","Log4NetLevel":"INFO ","HttpRequestNumber":1,"HttpRequestId":"9ab0fc0c-17e7-4013-86fd-df8ec195ffdf"}
{"@t":"2020-07-03T13:39:42.9769877Z","@mt":"{EndMessage} ({Duration}ms) [Timing {TimingId}]","EndMessage":"Completed.","Duration":4,"TimingId":"1e68c54","SourceContext":"Umbraco.Web.PublishedCache.NuCache.PublishedSnapshotService","ProcessId":19316,"ProcessName":"iisexpress","ThreadId":1,"AppDomainId":2,"AppDomainAppId":"LMW3SVC2ROOT","MachineName":"MSI","Log4NetLevel":"INFO ","HttpRequestNumber":1,"HttpRequestId":"9ab0fc0c-17e7-4013-86fd-df8ec195ffdf"}
{"@t":"2020-07-03T13:39:43.2539885Z","@mt":"Initializing Umbraco internal event handlers for cache refreshing.","SourceContext":"Umbraco.Web.Cache.DistributedCacheBinderComponent","ProcessId":19316,"ProcessName":"iisexpress","ThreadId":1,"AppDomainId":2,"AppDomainAppId":"LMW3SVC2ROOT","MachineName":"MSI","Log4NetLevel":"INFO ","HttpRequestNumber":1,"HttpRequestId":"9ab0fc0c-17e7-4013-86fd-df8ec195ffdf"}
{"@t":"2020-07-03T13:39:43.3099848Z","@mt":"Adding examine event handlers for {RegisteredIndexers} index providers.","RegisteredIndexers":3,"SourceContext":"Umbraco.Web.Search.ExamineComponent","ProcessId":19316,"ProcessName":"iisexpress","ThreadId":1,"AppDomainId":2,"AppDomainAppId":"LMW3SVC2ROOT","MachineName":"MSI","Log4NetLevel":"INFO ","HttpRequestNumber":1,"HttpRequestId":"9ab0fc0c-17e7-4013-86fd-df8ec195ffdf"}
{"@t":"2020-07-03T13:39:43.4529901Z","@mt":"Starting initialize async background thread.","SourceContext":"Umbraco.Web.Search.BackgroundIndexRebuilder","ProcessId":19316,"ProcessName":"iisexpress","ThreadId":1,"AppDomainId":2,"AppDomainAppId":"LMW3SVC2ROOT","MachineName":"MSI","Log4NetLevel":"INFO ","HttpRequestNumber":1,"HttpRequestId":"9ab0fc0c-17e7-4013-86fd-df8ec195ffdf"}
{"@t":"2020-07-03T13:39:43.4539903Z","@mt":"{EndMessage} ({Duration}ms) [Timing {TimingId}]","EndMessage":"Booted.","Duration":3275,"TimingId":"4fb706a","SourceContext":"Umbraco.Core.Runtime.CoreRuntime","ProcessId":19316,"ProcessName":"iisexpress","ThreadId":1,"AppDomainId":2,"AppDomainAppId":"LMW3SVC2ROOT","MachineName":"MSI","Log4NetLevel":"INFO ","HttpRequestNumber":1,"HttpRequestId":"9ab0fc0c-17e7-4013-86fd-df8ec195ffdf"}
{"@t":"2020-07-03T13:39:43.9189855Z","@mt":"New url {Url} detected, re-discovering application url.","Url":"http://localhost/umbraco","SourceContext":"Umbraco.Core.Sync.ApplicationUrlHelper","ProcessId":19316,"ProcessName":"iisexpress","ThreadId":6,"AppDomainId":2,"AppDomainAppId":"LMW3SVC2ROOT","MachineName":"MSI","Log4NetLevel":"INFO ","HttpRequestNumber":2,"HttpRequestId":"ac744307-7966-42d1-a46e-77865b8c3298"}
{"@t":"2020-07-03T13:39:43.9209871Z","@mt":"ApplicationUrl: {UmbracoAppUrl} (UmbracoModule request)","UmbracoAppUrl":"http://localhost/umbraco","SourceContext":"Umbraco.Core.Sync.ApplicationUrlHelper","ProcessId":19316,"ProcessName":"iisexpress","ThreadId":6,"AppDomainId":2,"AppDomainAppId":"LMW3SVC2ROOT","MachineName":"MSI","Log4NetLevel":"INFO ","HttpRequestNumber":2,"HttpRequestId":"ac744307-7966-42d1-a46e-77865b8c3298"}
{"@t":"2020-07-03T13:45:20.6519847Z","@mt":"{StartMessage} [Timing {TimingId}]","StartMessage":"Booting Umbraco 8.6.3.","TimingId":"d1a585b","SourceContext":"Umbraco.Core.Runtime.CoreRuntime","ProcessId":20272,"ProcessName":"iisexpress","ThreadId":1,"AppDomainId":2,"AppDomainAppId":"LMW3SVC2ROOT","MachineName":"MSI","Log4NetLevel":"INFO ","HttpRequestNumber":1,"HttpRequestId":"ee81b1c1-6dc0-42dd-b3e5-bdfbc974717b"}
{"@t":"2020-07-03T13:45:20.6789857Z","@mt":"Booting site '{HostingSiteName}', app '{HostingApplicationID}', path '{HostingPhysicalPath}', server '{MachineName}'.","HostingSiteName":"Emi-Center","HostingApplicationID":"/LM/W3SVC/2/ROOT","HostingPhysicalPath":"C:\\Users\\pisaq\\source\\repos\\Emi-Center\\","MachineName":"MSI","SourceContext":"Umbraco.Core.Runtime.CoreRuntime","ProcessId":20272,"ProcessName":"iisexpress","ThreadId":1,"AppDomainId":2,"AppDomainAppId":"LMW3SVC2ROOT","Log4NetLevel":"INFO ","HttpRequestNumber":1,"HttpRequestId":"ee81b1c1-6dc0-42dd-b3e5-bdfbc974717b"}
{"@t":"2020-07-03T13:45:20.9069848Z","@mt":"Acquiring.","SourceContext":"Umbraco.Core.Runtime.MainDom","ProcessId":20272,"ProcessName":"iisexpress","ThreadId":1,"AppDomainId":2,"AppDomainAppId":"LMW3SVC2ROOT","MachineName":"MSI","Log4NetLevel":"INFO ","HttpRequestNumber":1,"HttpRequestId":"ee81b1c1-6dc0-42dd-b3e5-bdfbc974717b"}
{"@t":"2020-07-03T13:45:20.9089888Z","@mt":"Acquired.","SourceContext":"Umbraco.Core.Runtime.MainDom","ProcessId":20272,"ProcessName":"iisexpress","ThreadId":1,"AppDomainId":2,"AppDomainAppId":"LMW3SVC2ROOT","MachineName":"MSI","Log4NetLevel":"INFO ","HttpRequestNumber":1,"HttpRequestId":"ee81b1c1-6dc0-42dd-b3e5-bdfbc974717b"}
{"@t":"2020-07-03T13:45:21.7529855Z","@mt":"{StartMessage} [Timing {TimingId}]","StartMessage":"Resolving composer types.","TimingId":"f764620","SourceContext":"Umbraco.Core.Runtime.CoreRuntime","ProcessId":20272,"ProcessName":"iisexpress","ThreadId":1,"AppDomainId":2,"AppDomainAppId":"LMW3SVC2ROOT","MachineName":"MSI","Log4NetLevel":"INFO ","HttpRequestNumber":1,"HttpRequestId":"ee81b1c1-6dc0-42dd-b3e5-bdfbc974717b"}
{"@t":"2020-07-03T13:45:22.0199887Z","@mt":"{EndMessage} ({Duration}ms) [Timing {TimingId}]","EndMessage":"Resolved.","Duration":265,"TimingId":"f764620","SourceContext":"Umbraco.Core.Runtime.CoreRuntime","ProcessId":20272,"ProcessName":"iisexpress","ThreadId":1,"AppDomainId":2,"AppDomainAppId":"LMW3SVC2ROOT","MachineName":"MSI","Log4NetLevel":"INFO ","HttpRequestNumber":1,"HttpRequestId":"ee81b1c1-6dc0-42dd-b3e5-bdfbc974717b"}
{"@t":"2020-07-03T13:45:22.8419873Z","@mt":"Registered with MainDom, localContentDbExists? {LocalContentDbExists}, localMediaDbExists? {LocalMediaDbExists}","LocalContentDbExists":true,"LocalMediaDbExists":true,"SourceContext":"Umbraco.Web.PublishedCache.NuCache.PublishedSnapshotService","ProcessId":20272,"ProcessName":"iisexpress","ThreadId":1,"AppDomainId":2,"AppDomainAppId":"LMW3SVC2ROOT","MachineName":"MSI","Log4NetLevel":"INFO ","HttpRequestNumber":1,"HttpRequestId":"ee81b1c1-6dc0-42dd-b3e5-bdfbc974717b"}
{"@t":"2020-07-03T13:45:22.8419873Z","@mt":"Creating the content store, localContentDbExists? {LocalContentDbExists}","LocalContentDbExists":true,"SourceContext":"Umbraco.Web.PublishedCache.NuCache.PublishedSnapshotService","ProcessId":20272,"ProcessName":"iisexpress","ThreadId":1,"AppDomainId":2,"AppDomainAppId":"LMW3SVC2ROOT","MachineName":"MSI","Log4NetLevel":"INFO ","HttpRequestNumber":1,"HttpRequestId":"ee81b1c1-6dc0-42dd-b3e5-bdfbc974717b"}
{"@t":"2020-07-03T13:45:22.8439869Z","@mt":"Creating the media store, localMediaDbExists? {LocalMediaDbExists}","LocalMediaDbExists":true,"SourceContext":"Umbraco.Web.PublishedCache.NuCache.PublishedSnapshotService","ProcessId":20272,"ProcessName":"iisexpress","ThreadId":1,"AppDomainId":2,"AppDomainAppId":"LMW3SVC2ROOT","MachineName":"MSI","Log4NetLevel":"INFO ","HttpRequestNumber":1,"HttpRequestId":"ee81b1c1-6dc0-42dd-b3e5-bdfbc974717b"}
{"@t":"2020-07-03T13:45:23.3439882Z","@mt":"{StartMessage} [Timing {TimingId}]","StartMessage":"Loading content from local cache file","TimingId":"ade276a","SourceContext":"Umbraco.Web.PublishedCache.NuCache.PublishedSnapshotService","ProcessId":20272,"ProcessName":"iisexpress","ThreadId":1,"AppDomainId":2,"AppDomainAppId":"LMW3SVC2ROOT","MachineName":"MSI","Log4NetLevel":"INFO ","HttpRequestNumber":1,"HttpRequestId":"ee81b1c1-6dc0-42dd-b3e5-bdfbc974717b"}
{"@t":"2020-07-03T13:45:23.3779855Z","@mt":"{EndMessage} ({Duration}ms) [Timing {TimingId}]","EndMessage":"Completed.","Duration":33,"TimingId":"ade276a","SourceContext":"Umbraco.Web.PublishedCache.NuCache.PublishedSnapshotService","ProcessId":20272,"ProcessName":"iisexpress","ThreadId":1,"AppDomainId":2,"AppDomainAppId":"LMW3SVC2ROOT","MachineName":"MSI","Log4NetLevel":"INFO ","HttpRequestNumber":1,"HttpRequestId":"ee81b1c1-6dc0-42dd-b3e5-bdfbc974717b"}
{"@t":"2020-07-03T13:45:23.3949869Z","@mt":"{StartMessage} [Timing {TimingId}]","StartMessage":"Loading media from local cache file","TimingId":"afaa8bb","SourceContext":"Umbraco.Web.PublishedCache.NuCache.PublishedSnapshotService","ProcessId":20272,"ProcessName":"iisexpress","ThreadId":1,"AppDomainId":2,"AppDomainAppId":"LMW3SVC2ROOT","MachineName":"MSI","Log4NetLevel":"INFO ","HttpRequestNumber":1,"HttpRequestId":"ee81b1c1-6dc0-42dd-b3e5-bdfbc974717b"}
{"@t":"2020-07-03T13:45:23.3989871Z","@mt":"{EndMessage} ({Duration}ms) [Timing {TimingId}]","EndMessage":"Completed.","Duration":3,"TimingId":"afaa8bb","SourceContext":"Umbraco.Web.PublishedCache.NuCache.PublishedSnapshotService","ProcessId":20272,"ProcessName":"iisexpress","ThreadId":1,"AppDomainId":2,"AppDomainAppId":"LMW3SVC2ROOT","MachineName":"MSI","Log4NetLevel":"INFO ","HttpRequestNumber":1,"HttpRequestId":"ee81b1c1-6dc0-42dd-b3e5-bdfbc974717b"}
{"@t":"2020-07-03T13:45:23.6239870Z","@mt":"Initializing Umbraco internal event handlers for cache refreshing.","SourceContext":"Umbraco.Web.Cache.DistributedCacheBinderComponent","ProcessId":20272,"ProcessName":"iisexpress","ThreadId":1,"AppDomainId":2,"AppDomainAppId":"LMW3SVC2ROOT","MachineName":"MSI","Log4NetLevel":"INFO ","HttpRequestNumber":1,"HttpRequestId":"ee81b1c1-6dc0-42dd-b3e5-bdfbc974717b"}
{"@t":"2020-07-03T13:45:23.6789867Z","@mt":"Adding examine event handlers for {RegisteredIndexers} index providers.","RegisteredIndexers":3,"SourceContext":"Umbraco.Web.Search.ExamineComponent","ProcessId":20272,"ProcessName":"iisexpress","ThreadId":1,"AppDomainId":2,"AppDomainAppId":"LMW3SVC2ROOT","MachineName":"MSI","Log4NetLevel":"INFO ","HttpRequestNumber":1,"HttpRequestId":"ee81b1c1-6dc0-42dd-b3e5-bdfbc974717b"}
{"@t":"2020-07-03T13:45:23.7099858Z","@mt":"Starting initialize async background thread.","SourceContext":"Umbraco.Web.Search.BackgroundIndexRebuilder","ProcessId":20272,"ProcessName":"iisexpress","ThreadId":1,"AppDomainId":2,"AppDomainAppId":"LMW3SVC2ROOT","MachineName":"MSI","Log4NetLevel":"INFO ","HttpRequestNumber":1,"HttpRequestId":"ee81b1c1-6dc0-42dd-b3e5-bdfbc974717b"}
{"@t":"2020-07-03T13:45:23.7109857Z","@mt":"{EndMessage} ({Duration}ms) [Timing {TimingId}]","EndMessage":"Booted.","Duration":3070,"TimingId":"d1a585b","SourceContext":"Umbraco.Core.Runtime.CoreRuntime","ProcessId":20272,"ProcessName":"iisexpress","ThreadId":1,"AppDomainId":2,"AppDomainAppId":"LMW3SVC2ROOT","MachineName":"MSI","Log4NetLevel":"INFO ","HttpRequestNumber":1,"HttpRequestId":"ee81b1c1-6dc0-42dd-b3e5-bdfbc974717b"}
{"@t":"2020-07-03T13:45:24.1829847Z","@mt":"New url {Url} detected, re-discovering application url.","Url":"http://localhost/umbraco","SourceContext":"Umbraco.Core.Sync.ApplicationUrlHelper","ProcessId":20272,"ProcessName":"iisexpress","ThreadId":5,"AppDomainId":2,"AppDomainAppId":"LMW3SVC2ROOT","MachineName":"MSI","Log4NetLevel":"INFO ","HttpRequestNumber":2,"HttpRequestId":"03b6c597-5109-48ea-8c85-7b42098f9362"}
{"@t":"2020-07-03T13:45:24.1849878Z","@mt":"ApplicationUrl: {UmbracoAppUrl} (UmbracoModule request)","UmbracoAppUrl":"http://localhost/umbraco","SourceContext":"Umbraco.Core.Sync.ApplicationUrlHelper","ProcessId":20272,"ProcessName":"iisexpress","ThreadId":5,"AppDomainId":2,"AppDomainAppId":"LMW3SVC2ROOT","MachineName":"MSI","Log4NetLevel":"INFO ","HttpRequestNumber":2,"HttpRequestId":"03b6c597-5109-48ea-8c85-7b42098f9362"}
